xyw_utils/__init__.py
xyw_utils/data.py
xyw_utils/errors.py
xyw_utils/math.py
xyw_utils/path.py
xyw_utils/pdf.py
xyw_utils/vehicle_test.py
xyw_utils/examples/30-50.xls
xyw_utils/examples/60-0.xls
xyw_utils/examples/CCBC.csv
xyw_utils/examples/returnability_test.xlsx
xyw_utils/examples/steady_static_circular_test.xlsx
xyw_utils/examples/steering_efforts_test.xlsx
xyw_utils/examples/imgs/001.jpg
xyw_utils/examples/imgs/002.jpg
xyw_utils/examples/imgs/003.jpg
xyw_utils/examples/imgs/004.jpg
xyw_utils/examples/imgs/005.jpg
xyw_utils-0.0.10.dist-info/LICENSE
xyw_utils-0.0.10.dist-info/METADATA
xyw_utils-0.0.10.dist-info/WHEEL
xyw_utils-0.0.10.dist-info/top_level.txt
xyw_utils-0.0.10.dist-info/RECORD
