Metadata-Version: 2.1
Name: xyw-utils
Version: 0.0.10
Summary: 个人工具合集
Home-page: UNKNOWN
Author: 二炜
Author-email: 1174543101@qq.com
License: UNKNOWN
Platform: UNKNOWN
Classifier: Programming Language :: Python :: 3
Classifier: License :: OSI Approved :: MIT License
Classifier: Operating System :: OS Independent
Requires-Dist: pandas
Requires-Dist: numpy
Requires-Dist: scipy
Requires-Dist: pygal
Requires-Dist: cairosvg
Requires-Dist: cssselect2
Requires-Dist: pikepdf
Requires-Dist: img2pdf
Requires-Dist: openpyxl
Requires-Dist: xlwt
Requires-Dist: xlsxwriter
Requires-Dist: matplotlib
